earthdaily/__init__.py
earthdaily/_api_requester.py
earthdaily/_auth_client.py
earthdaily/_downloader.py
earthdaily/_eds_client.py
earthdaily/_eds_config.py
earthdaily/_eds_logging.py
earthdaily/_eds_models.py
earthdaily/_http_client.py
earthdaily/_uploader.py
earthdaily/_zipper.py
earthdaily/exceptions.py
earthdaily/datacube/README.md
earthdaily/datacube/__init__.py
earthdaily/datacube/_builder.py
earthdaily/datacube/_datacube.py
earthdaily/datacube/_datacube_service.py
earthdaily/datacube/_geometry.py
earthdaily/datacube/_indices.py
earthdaily/datacube/_masking.py
earthdaily/datacube/_operations.py
earthdaily/datacube/_temporal.py
earthdaily/datacube/_visualization.py
earthdaily/datacube/_whittaker.py
earthdaily/datacube/_zonal.py
earthdaily/datacube/constants.py
earthdaily/datacube/exceptions.py
earthdaily/datacube/models.py
earthdaily/legacy/__init__.py
earthdaily/legacy/accessor/__init__.py
earthdaily/legacy/accessor/whittaker/__init__.py
earthdaily/legacy/core/__init__.py
earthdaily/legacy/core/_options.py
earthdaily/legacy/datasets/__init__.py
earthdaily/legacy/datasets/data/__init__.py
earthdaily/legacy/datasets/data/pivot.geojson
earthdaily/legacy/datasets/data/pivot_corumba.geojson
earthdaily/legacy/earthdatastore/__init__.py
earthdaily/legacy/earthdatastore/_filter_duplicate.py
earthdaily/legacy/earthdatastore/_scales_collections.py
earthdaily/legacy/earthdatastore/parallel_search.py
earthdaily/legacy/earthdatastore/cube_utils/__init__.py
earthdaily/legacy/earthdatastore/cube_utils/_zonal.py
earthdaily/legacy/earthdatastore/cube_utils/geometry_manager.py
earthdaily/legacy/earthdatastore/cube_utils/preprocessing.py
earthdaily/legacy/earthdatastore/cube_utils/asset_mapper/__init__.py
earthdaily/legacy/earthdatastore/cube_utils/asset_mapper/asset_mapper_config.json
earthdaily/legacy/earthdatastore/cube_utils/harmonizer/__init__.py
earthdaily/legacy/earthdatastore/mask/__init__.py
earthdaily/ordering/README.md
earthdaily/ordering/__init__.py
earthdaily-1.8.0.dist-info/METADATA
earthdaily-1.8.0.dist-info/WHEEL
earthdaily-1.8.0.dist-info/licenses/LICENSE
earthdaily-1.8.0.dist-info/RECORD
