Metadata-Version: 2.4
Name: earthdaily
Version: 1.8.0
Summary: EarthDaily Python Client
Author-email: EarthDaily <info@earthdaily.com>
License-Expression: MIT
License-File: LICENSE
Requires-Python: <3.15,>=3.10
Requires-Dist: requests>=2.32.4
Requires-Dist: toml>=0.10.2
Provides-Extra: datacube
Requires-Dist: dask; extra == 'datacube'
Requires-Dist: geopandas>=1.0.1; extra == 'datacube'
Requires-Dist: matplotlib>=3.0.0; extra == 'datacube'
Requires-Dist: numpy>=2.2.2; extra == 'datacube'
Requires-Dist: odc-stac>=0.4.0; extra == 'datacube'
Requires-Dist: pandas>=2.2.3; extra == 'datacube'
Requires-Dist: pystac>=1.12.1; extra == 'datacube'
Requires-Dist: rasterio>=1.4.3; extra == 'datacube'
Requires-Dist: rioxarray>=0.18.2; extra == 'datacube'
Requires-Dist: scipy>=1.15.1; extra == 'datacube'
Requires-Dist: spyndex>=0.7.0; extra == 'datacube'
Requires-Dist: xarray>=2025.1.2; extra == 'datacube'
Provides-Extra: legacy
Requires-Dist: dask-image>=2024.5.3; extra == 'legacy'
Requires-Dist: dask<2025.3.0; extra == 'legacy'
Requires-Dist: flox<0.11.0,>=0.10.0; extra == 'legacy'
Requires-Dist: geopandas>=1.0.1; extra == 'legacy'
Requires-Dist: joblib>=1.4.2; extra == 'legacy'
Requires-Dist: numpy>=2.2.2; extra == 'legacy'
Requires-Dist: odc-stac>=0.3.11; extra == 'legacy'
Requires-Dist: pandas>=2.2.3; extra == 'legacy'
Requires-Dist: protobuf>=5.29.5; extra == 'legacy'
Requires-Dist: psutil>=6.1.1; extra == 'legacy'
Requires-Dist: pyarrow>=19.0.0; extra == 'legacy'
Requires-Dist: pystac-client>=0.8.6; extra == 'legacy'
Requires-Dist: pystac>=1.12.1; extra == 'legacy'
Requires-Dist: rasterio>=1.4.3; extra == 'legacy'
Requires-Dist: rioxarray>=0.18.2; extra == 'legacy'
Requires-Dist: scipy>=1.15.1; extra == 'legacy'
Requires-Dist: spyndex>=0.7.0; extra == 'legacy'
Requires-Dist: stackstac>=0.5.1; extra == 'legacy'
Requires-Dist: tqdm>=4.66.5; extra == 'legacy'
Requires-Dist: xarray>=2025.1.2; extra == 'legacy'
Provides-Extra: ordering
Requires-Dist: pystac>=1.12.1; extra == 'ordering'
Provides-Extra: platform
Requires-Dist: pystac-client>=0.8.6; extra == 'platform'
Requires-Dist: pystac>=1.12.1; extra == 'platform'
Requires-Dist: tqdm>=4.66.5; extra == 'platform'
Provides-Extra: utils
Requires-Dist: ipykernel>=7.0.0; extra == 'utils'
Requires-Dist: jupyter>=1.0.0; extra == 'utils'
Requires-Dist: python-dotenv>=1.0.0; extra == 'utils'
